{"rows_added":[],"rows_removed":[],"rows_changed":{"0":{"":["Eshana seems on the verge of panicking.\r\n\r\n\u203bPlease note that the difficulty of this quest has been synced to your current level. Furthermore, you may not proceed with a class or job that is different from when you accepted this quest.","Eshana seems on the verge of panicking.\n\n\u203bPlease note that the difficulty of this quest has been synced to your current level. Furthermore, you may not proceed with a class or job that is different from when you accepted this quest."]},"54":{"":["<gasp> Well, that's it then.\r\nI'm done for...","<gasp> Well, that's it then.\nI'm done for..."]}}}