{"rows_added":[],"rows_removed":[],"rows_changed":{"2":{"":["As usual, Gigi assists with the evaluation of your work. However, in an unusual turn of events, your fire brand appears to trigger bizarre pyromaniac tendencies hidden deep within the mammet's soul. Nevertheless, Serendipity assures you that there is no need for concern, and that she will see that Roroton receives his order without incident.\r\n\r\n\u203bThe next goldsmith quest will be available from Serendipity upon reaching level 40.","As usual, Gigi assists with the evaluation of your work. However, in an unusual turn of events, your fire brand appears to trigger bizarre pyromaniac tendencies hidden deep within the mammet's soul. Nevertheless, Serendipity assures you that there is no need for concern, and that she will see that Roroton receives his order without incident.\n\n\u203bThe next goldsmith quest will be available from Serendipity upon reaching level 40."]},"55":{"":["NE\u203bGIGIGI\u2605\u203b...\r\nFiRe...BrAnD...bUrN, bUrN, mAkE iT bUrN tHeM!","NE\u203bGIGIGI\u2605\u203b...\nFiRe...BrAnD...bUrN, bUrN, mAkE iT bUrN tHeM!"]}}}