{"rows_added":[20139],"rows_removed":[],"rows_changed":{"20099":{"File":["","music/ex5/BGM_EX5_Ban_11.scd"],"Priority":["0","1"],"DisableRestartTimeOut":["False","True"],"DisableRestart":["False","True"],"DisableRestartResetTime":["0","90"]},"20105":{"File":["","music/ex5/BGM_EX5_Ban_12.scd"],"Priority":["0","1"],"PassEnd":["False","True"],"DisableRestartResetTime":["0","90"]},"20134":{"File":["","music/ex5/BGM_EX5_Ban_13.scd"],"Priority":["0","1"],"PassEnd":["False","True"],"DisableRestartResetTime":["0","90"]},"20135":{"File":["","music/ex5/BGM_EX5_Ban_14.scd"],"Priority":["0","1"],"PassEnd":["False","True"],"DisableRestartResetTime":["0","90"]},"20136":{"File":["","music/ex5/BGM_EX5_Ban_15.scd"],"Priority":["0","1"],"PassEnd":["False","True"],"DisableRestartResetTime":["0","90"]},"20137":{"File":["","music/ex5/BGM_EX5_Ban_16.scd"],"Priority":["0","1"],"PassEnd":["False","True"],"DisableRestartResetTime":["0","90"]}}}