{"rows_added":[],"rows_removed":[],"rows_changed":{"20169":{"File":["","music/ex4/BGM_EX4_WKS_01.scd"],"Priority":["0","1"],"PassEnd":["False","True"],"DisableRestartResetTime":["0","90"]},"20170":{"File":["","music/ex4/BGM_EX4_WKS_02.scd"],"Priority":["0","1"],"PassEnd":["False","True"],"DisableRestartResetTime":["0","90"]},"20171":{"File":["","music/ex4/BGM_EX4_WKS_03.scd"],"Priority":["0","1"],"PassEnd":["False","True"],"DisableRestartResetTime":["0","90"]},"20172":{"File":["","music/ex4/BGM_EX4_WKS_04.scd"],"Priority":["0","1"],"PassEnd":["False","True"],"DisableRestartResetTime":["0","90"]},"20173":{"File":["","music/ex4/BGM_EX4_WKS_05.scd"],"Priority":["0","1"],"PassEnd":["False","True"],"DisableRestartResetTime":["0","90"]},"20174":{"File":["","music/ex4/BGM_EX4_WKS_06.scd"],"Priority":["0","1"],"PassEnd":["False","True"],"DisableRestartResetTime":["0","90"]},"20175":{"File":["","music/ffxiv/BGM_Ride_WKS01.scd"],"Priority":["0","1"],"PassEnd":["False","True"],"DisableRestartResetTime":["0","90"],"SpecialMode":["0","2"]}}}