{"rows_added":[],"rows_removed":[],"rows_changed":{"210":{"Name":["","Abridged Too Far"],"Unknown0":["0","5459"],"RequiredLevel":["0","100"]},"606":{"Name":["Best-Laid Schemes","Best-laid Schemes"]},"2353":{"Name":["","A Need for Speed"],"Unknown0":["0","5446"],"Unknown1":["0","86"],"Icon":["0","61411"],"Cutscene[0]":["0","3804"],"RequiredLevel":["0","100"]},"2354":{"Name":["","Meteorites and Meteor-wrongs"],"Unknown0":["0","5447"],"Unknown1":["0","86"],"Icon":["0","61411"],"Cutscene[0]":["0","3805"],"Cutscene[1]":["0","3806"],"Cutscene[2]":["0","3807"],"RequiredLevel":["0","100"]},"2511":{"Name":["","A Spellbinding Read"],"Unknown0":["0","5441"],"Unknown1":["0","107"],"Icon":["0","61419"],"Cutscene[0]":["0","3877"],"Cutscene[1]":["0","3875"],"RequiredLevel":["0","90"]},"2512":{"Name":["","Starting a New Chapter"],"Unknown0":["0","5442"],"Unknown1":["0","107"],"Icon":["0","61411"],"Cutscene[0]":["0","3876"],"RequiredLevel":["0","90"]},"3103":{"Name":["The Best-Laid Plans","The Best-laid Plans"]},"5312":{"Name":["\u30a8\u30c3\u30b0\u30cf\u30f3\u30c8\u3068\u8b0e\u306e\u8349","Of Weeds and Whimsy"],"Icon":["61411","61419"]},"7727":{"Name":["","*The Merchant's Tale*"],"Unknown0":["0","1066"],"Unknown1":["0","310"],"Icon":["0","61846"],"Cutscene[0]":["0","3878"],"Cutscene[1]":["0","3885"],"Cutscene[2]":["0","3886"],"Cutscene[3]":["0","3887"],"Cutscene[4]":["0","3888"],"Cutscene[5]":["0","3881"],"Cutscene[6]":["0","3882"],"Cutscene[7]":["0","3883"],"Cutscene[8]":["0","3884"],"RequiredLevel":["0","90"]},"7728":{"Name":["","*The Merchant's Tale* (Advanced)"],"Unknown0":["0","1084"],"Unknown1":["0","310"],"Icon":["0","61846"],"Cutscene[0]":["0","3879"],"RequiredLevel":["0","100"]},"7729":{"Name":["","Another Merchant's Tale"],"Unknown0":["0","1079"],"Unknown1":["0","310"],"Icon":["0","61846"],"Cutscene[0]":["0","3880"],"RequiredLevel":["0","100"]}}}