{"rows_added":[],"rows_removed":[],"rows_changed":{"1315":{"Name":["","m6d1"],"Bg":["","ex5/07_mid_m6/dun/m6d1/level/m6d1"],"PlaceNameRegionIcon":["0","122032"],"PlaceNameIcon":["0","124077"],"FixedTime":["0","-1"],"PlaceNameRegion":["0","2405"],"PlaceNameZone":["0","519"],"PlaceName":["0","5372"],"Map":["0","1114"],"ContentFinderCondition":["0","1066"],"BGM":["0","1001"],"BattalionMode":["0","1"],"LoadingImage":["0","37"],"ExclusiveType":["0","2"],"TerritoryIntendedUse":["0","4"],"ExVersion":["0","5"],"AchievementIndex":["0","-1"],"PCSearch":["False","True"],"IsInUse":["False","True"],"Unknown13":["False","True"],"Unknown15":["False","True"],"Unknown16":["False","True"]},"1316":{"Name":["","m6d1_2"],"Bg":["","ex5/07_mid_m6/dun/m6d1/level/m6d1"],"PlaceNameRegionIcon":["0","122032"],"PlaceNameIcon":["0","124078"],"FixedTime":["0","-1"],"PlaceNameRegion":["0","2405"],"PlaceNameZone":["0","519"],"PlaceName":["0","5372"],"Map":["0","1162"],"ContentFinderCondition":["0","1084"],"BGM":["0","1001"],"BattalionMode":["0","1"],"LoadingImage":["0","37"],"ExclusiveType":["0","2"],"TerritoryIntendedUse":["0","4"],"ExVersion":["0","5"],"AchievementIndex":["0","-1"],"PCSearch":["False","True"],"IsInUse":["False","True"],"Unknown13":["False","True"],"Unknown15":["False","True"],"Unknown16":["False","True"]},"1317":{"Name":["","m6d1_3"],"Bg":["","ex5/07_mid_m6/dun/m6d1/level/m6d1"],"PlaceNameRegionIcon":["0","122033"],"PlaceNameIcon":["0","124079"],"FixedTime":["0","-1"],"PlaceNameRegion":["0","2405"],"PlaceNameZone":["0","519"],"PlaceName":["0","5474"],"Map":["0","1164"],"ContentFinderCondition":["0","1079"],"BGM":["0","1001"],"BattalionMode":["0","1"],"LoadingImage":["0","37"],"ExclusiveType":["0","2"],"TerritoryIntendedUse":["0","57"],"ExVersion":["0","5"],"AchievementIndex":["0","-1"],"PCSearch":["False","True"],"IsInUse":["False","True"],"Unknown13":["False","True"],"Unknown15":["False","True"],"Unknown16":["False","True"]},"1336":{"Aetheryte":["0","2"]},"1337":{"Name":["","m6e1"],"Bg":["","ex5/07_mid_m6/evt/m6e1/level/m6e1"],"ArrayEventHandler":["0","855060"],"PlaceNameRegionIcon":["0","-1"],"PlaceNameIcon":["0","-1"],"Aetheryte":["0","182"],"FixedTime":["0","-1"],"PlaceNameRegion":["0","2405"],"PlaceNameZone":["0","519"],"PlaceName":["0","4764"],"Map":["0","1124"],"BGM":["0","20193"],"BattalionMode":["0","1"],"LoadingImage":["0","37"],"TerritoryIntendedUse":["0","15"],"ExVersion":["0","5"],"AchievementIndex":["0","-1"],"PCSearch":["False","True"],"IsInUse":["False","True"],"Unknown13":["False","True"],"Unknown15":["False","True"],"Unknown16":["False","True"]}}}