{"rows_added":[721869,721870,721871,721872,721873,721874,721875,721876,721877,721878,721879,721880,721881,721882,721883,721884,721885,721886,721887,721888,721889,721890,721891],"rows_removed":[],"rows_changed":{"720986":{"Script[8].ScriptInstruction":["","QST_SUBGTN102"],"Script[8].ScriptArg":["0","70921"]},"721282":{"Script[24].ScriptInstruction":["","DESCRIPTION0"],"Script[24].ScriptArg":["0","3604509"]},"721330":{"Script[21].ScriptInstruction":["","DESCRIPTION0"],"Script[21].ScriptArg":["0","3604509"]},"721570":{"Script[22].ScriptInstruction":["","DESCRIPTION0"],"Script[22].ScriptArg":["0","3604509"]},"721606":{"Script[28].ScriptInstruction":["","DESCRIPTION0"],"Script[28].ScriptArg":["0","3604509"]},"721647":{"Script[5].ScriptInstruction":["","QST_KINGMK101"],"Script[5].ScriptArg":["0","71006"],"Script[6].ScriptInstruction":["","QST_KINGMK102"],"Script[6].ScriptArg":["0","71007"],"Script[7].ScriptInstruction":["","QUEST_SEQ_FINISH"],"Script[7].ScriptArg":["0","255"]},"721649":{"Script[10].ScriptInstruction":["","QST_KINGMK101"],"Script[10].ScriptArg":["0","71006"],"Script[11].ScriptInstruction":["","QST_KINGMK102"],"Script[11].ScriptArg":["0","71007"]},"721669":{"Script[28].ScriptInstruction":["","DESCRIPTION0"],"Script[28].ScriptArg":["0","3604509"]},"721672":{"Script[18].ScriptInstruction":["","LOC_ENPC_LASTYEAR_06"],"Script[18].ScriptArg":["0","1059517"]},"721711":{"Script[15].ScriptInstruction":["","DESCRIPTION0"],"Script[15].ScriptArg":["0","3604509"]},"721738":{"Script[24].ScriptInstruction":["","DESCRIPTION0"],"Script[24].ScriptArg":["0","3604509"]},"721793":{"Script[5].ScriptInstruction":["LOC_BGM0","ID_BATTLE_SPHENE_HARD"],"Script[5].ScriptArg":["20034","1017"],"Script[6].ScriptInstruction":["ID_BATTLE_SPHENE_HARD","ID_BATTLE_CLOUDOFDARKNESS_HARD"],"Script[6].ScriptArg":["1017","1010"],"Script[7].ScriptInstruction":["ID_BATTLE_CLOUDOFDARKNESS_HARD","ID_BATTLE_ULTIMATE_EDEN"],"Script[7].ScriptArg":["1010","1006"],"Script[8].ScriptInstruction":["ID_BATTLE_ULTIMATE_EDEN","SCREEN_IMAGE_SPHENE_HARD"],"Script[8].ScriptArg":["1006","1359"],"Script[9].ScriptInstruction":["SCREEN_IMAGE_SPHENE_HARD","SCREEN_IMAGE_CLOUDOFDARKNESS_HARD"],"Script[9].ScriptArg":["1359","1362"],"Script[10].ScriptInstruction":["SCREEN_IMAGE_CLOUDOFDARKNESS_HARD","SCREEN_IMAGE_ULTIMATE_EDEN"],"Script[10].ScriptArg":["1362","1361"],"Script[11].ScriptInstruction":["SCREEN_IMAGE_ULTIMATE_EDEN","QST_LUCKRA302"],"Script[11].ScriptArg":["1361","69512"],"Script[12].ScriptInstruction":["QST_LUCKRA302","QST_LUCKRA305"],"Script[12].ScriptArg":["69512","69515"],"Script[13].ScriptInstruction":["QST_LUCKRA305","LOC_BGM1"],"Script[13].ScriptArg":["69515","212"],"Script[14].ScriptInstruction":["LOC_BGM1","LOC_ACTOR0"],"Script[14].ScriptArg":["212","1052534"],"Script[15].ScriptInstruction":["LOC_ACTOR0","ID_BATTLE_DEFENDER_HARD"],"Script[15].ScriptArg":["1052534","1031"],"Script[16].ScriptInstruction":["ID_BATTLE_DEFENDER_HARD","SCREEN_IMAGE_DEFENDER_HARD"],"Script[16].ScriptArg":["1031","1449"],"Script[17].ScriptInstruction":["SCREEN_IMAGE_DEFENDER_HARD","ID_BATTLE_ETERNAL_DARKNESS_HARD"],"Script[17].ScriptArg":["1449","1062"],"Script[18].ScriptInstruction":["ID_BATTLE_ETERNAL_DARKNESS_HARD","SCREEN_IMAGE_ETERNAL_DARKNESS_HARD"],"Script[18].ScriptArg":["1062","1469"],"Script[19].ScriptInstruction":["SCREEN_IMAGE_ETERNAL_DARKNESS_HARD","ID_BATTLE_KGR_HARD"],"Script[19].ScriptArg":["1469","1044"],"Script[20].ScriptInstruction":["ID_BATTLE_KGR_HARD","SCREEN_IMAGE_KGR_HARD"],"Script[20].ScriptArg":["1044","1471"],"Script[21].ScriptInstruction":["SCREEN_IMAGE_KGR_HARD","ID_BATTLE_GLASYALABOLAS_HARD"],"Script[21].ScriptArg":["1471","1077"],"Script[22].ScriptInstruction":["ID_BATTLE_GLASYALABOLAS_HARD","SCREEN_IMAGE_GLASYALABOLAS_HARD"],"Script[22].ScriptArg":["1077","1562"],"Script[23].ScriptInstruction":["SCREEN_IMAGE_GLASYALABOLAS_HARD","ID_BATTLE_ENUO_HARD"],"Script[23].ScriptArg":["1562","1116"],"Script[24].ScriptInstruction":["","SCREEN_IMAGE_ENUO_HARD"],"Script[24].ScriptArg":["0","1610"],"Script[25].ScriptInstruction":["","ID_BATTLE_ULTIMATE_CFC"],"Script[25].ScriptArg":["0","1094"],"Script[26].ScriptInstruction":["","SCREEN_IMAGE_ULTIMATE_CFC"],"Script[26].ScriptArg":["0","1612"],"Script[27].ScriptInstruction":["","QST_STMBDR205"],"Script[27].ScriptArg":["0","68571"],"Script[28].ScriptInstruction":["","LOC_SE1"],"Script[28].ScriptArg":["0","426"]},"721805":{"Script[13].ScriptInstruction":["","DESCRIPTION0"],"Script[13].ScriptArg":["0","3604509"]},"721808":{"Script[18].ScriptInstruction":["LOC_BOU_KIRIN_TANK","BGM_KIRIN"],"Script[18].ScriptArg":["24850","20220"],"Script[19].ScriptInstruction":["LOC_BOU_KIRIN_MEIL","BGM_OMEGAULTIMA"],"Script[19].ScriptArg":["24851","634"],"Script[20].ScriptInstruction":["LOC_BOU_KIRIN_MELEE","BGM_KAM"],"Script[20].ScriptArg":["24852","20221"],"Script[21].ScriptInstruction":["LOC_BOU_KIRIN_ROGUE","BGM_EALD"],"Script[21].ScriptArg":["24853","20222"],"Script[22].ScriptInstruction":["LOC_BOU_KIRIN_RANGE","QST_KINGEA301"],"Script[22].ScriptArg":["24854","71015"],"Script[23].ScriptInstruction":["BGM_KIRIN","QST_KINGEA302"],"Script[23].ScriptArg":["20220","71016"],"Script[24].ScriptInstruction":["BGM_OMEGAULTIMA","BGM_SHANTO"],"Script[24].ScriptArg":["634","20266"],"Script[25].ScriptInstruction":["BGM_KAM","BGM_ALEX"],"Script[25].ScriptArg":["20221","20271"],"Script[26].ScriptInstruction":["BGM_EALD","BGM_PROMA"],"Script[26].ScriptArg":["20222","20273"],"Script[27].ScriptInstruction":["","BGM_SHIN01"],"Script[27].ScriptArg":["0","20274"],"Script[28].ScriptInstruction":["","BGM_SHIN02"],"Script[28].ScriptArg":["0","20275"]},"721816":{"Script[28].ScriptInstruction":["","SCREEN_IMAGE_FINISH"],"Script[28].ScriptArg":["0","1640"],"Script[29].ScriptInstruction":["","LOGMSG_MISSION_DESCRIPTION"],"Script[29].ScriptArg":["0","11589"]},"721821":{"Script[2].ScriptInstruction":["","TERRITORY_O6B2"],"Script[2].ScriptArg":["0","1346"],"Script[3].ScriptInstruction":["","QUEST01"],"Script[3].ScriptArg":["0","71047"]},"721824":{"Script[22].ScriptInstruction":["","C1W4_LOC_POS_1"],"Script[22].ScriptArg":["0","12564919"],"Script[23].ScriptInstruction":["","C1W4_LOC_POS_2"],"Script[23].ScriptArg":["0","12564920"],"Script[24].ScriptInstruction":["","C1W4_LOC_POS_3"],"Script[24].ScriptArg":["0","12564921"],"Script[25].ScriptInstruction":["","C1W4_LOC_POS_4"],"Script[25].ScriptArg":["0","12564922"],"Script[26].ScriptInstruction":["","C1W4_LOC_POS_5"],"Script[26].ScriptArg":["0","12564923"],"Script[27].ScriptInstruction":["","C1W4_LOC_POS_6"],"Script[27].ScriptArg":["0","12564924"],"Script[28].ScriptInstruction":["","C1W4_LOC_POS_7"],"Script[28].ScriptArg":["0","12564925"]},"721825":{"Script[3].ScriptInstruction":["","QUEST02"],"Script[3].ScriptArg":["0","71047"],"Script[4].ScriptInstruction":["","QUEST03"],"Script[4].ScriptArg":["0","71053"],"Script[5].ScriptInstruction":["","CONTENT02"],"Script[5].ScriptArg":["0","1093"],"Script[6].ScriptInstruction":["","CONTENT03"],"Script[6].ScriptArg":["0","1114"]},"721842":{"Script[0].ScriptArg":["164","176"],"Script[1].ScriptArg":["70912","71004"],"Script[2].ScriptArg":["152","164"],"Script[3].ScriptArg":["70721","70912"]},"721845":{"Script[2].ScriptInstruction":["","LOC_QUEST_KINGMK101"],"Script[2].ScriptArg":["0","71006"]},"721852":{"Script[3].ScriptInstruction":["REWARD_WKS_72SUBQUEST_UNLOCK","TARGET_MUMUKO_75"],"Script[3].ScriptArg":["541","1056851"],"Script[4].ScriptInstruction":["REWARD_WKS_73SUBQUEST_UNLOCK","REWARD_WKS_72SUBQUEST_UNLOCK"],"Script[4].ScriptArg":["540","541"],"Script[5].ScriptInstruction":["REWARD_WKS_74_SUBQUEST_UNLOCK","REWARD_WKS_73SUBQUEST_UNLOCK"],"Script[5].ScriptArg":["595","540"],"Script[6].ScriptInstruction":["QST_KINGWZ001","REWARD_WKS_74_SUBQUEST_UNLOCK"],"Script[6].ScriptArg":["70859","595"],"Script[7].ScriptInstruction":["QST_KINGWZ002","REWARD_WKS_75_SUBQUEST_UNLOCK"],"Script[7].ScriptArg":["70860","636"],"Script[8].ScriptInstruction":["QST_KINGWZ201","QST_KINGWZ001"],"Script[8].ScriptArg":["70947","70859"],"Script[9].ScriptInstruction":["QST_KINGWZ204","QST_KINGWZ002"],"Script[9].ScriptArg":["70950","70860"],"Script[10].ScriptInstruction":["QST_KINGWZ202","QST_KINGWZ201"],"Script[10].ScriptArg":["70948","70947"],"Script[11].ScriptInstruction":["QST_KINGWZ203","QST_KINGWZ204"],"Script[11].ScriptArg":["70949","70950"],"Script[12].ScriptInstruction":["QST_KINGWZ301","QST_KINGWZ202"],"Script[12].ScriptArg":["70986","70948"],"Script[13].ScriptInstruction":["QST_KINGWZ302","QST_KINGWZ203"],"Script[13].ScriptArg":["70987","70949"],"Script[14].ScriptInstruction":["QST_KINGWZ303","QST_KINGWZ301"],"Script[14].ScriptArg":["70988","70986"],"Script[15].ScriptInstruction":["","QST_KINGWZ302"],"Script[15].ScriptArg":["0","70987"],"Script[16].ScriptInstruction":["","QST_KINGWZ303"],"Script[16].ScriptArg":["0","70988"],"Script[17].ScriptInstruction":["","QST_KINGWZ401"],"Script[17].ScriptArg":["0","71022"],"Script[18].ScriptInstruction":["","QST_KINGWZ402"],"Script[18].ScriptArg":["0","71023"]},"721866":{"Script[0].ScriptInstruction":["","ENPC_CHK_GUIDE_ETHELIA"],"Script[0].ScriptArg":["0","1058139"],"Name":["","FesSum2026Guide_00970"],"Unknown12":["False","True"]},"721867":{"Script[0].ScriptInstruction":["QST_KINGWK302","QST_KINGWZ301"],"Script[0].ScriptArg":["70985","70986"],"Script[1].ScriptInstruction":["QST_KINGWZ301","QST_KINGWK302"],"Script[1].ScriptArg":["70986","70985"],"Script[2].ScriptInstruction":["TARGET_DYLISE_00","QST_KINGWK401"],"Script[2].ScriptArg":["1053353","71019"],"Script[3].ScriptInstruction":["TARGET_DYLISE_01","QST_KINGWK402"],"Script[3].ScriptArg":["1052655","71020"],"Script[4].ScriptInstruction":["TARGET_DYLISE_02","BIND_COMMAND_01"],"Script[4].ScriptArg":["1052670","12239593"],"Script[5].ScriptInstruction":["TARGET_DYLISE_03","TARGET_DYLISE_00"],"Script[5].ScriptArg":["1052656","1053353"],"Script[6].ScriptInstruction":["TARGET_DYLISE_04","TARGET_DYLISE_01"],"Script[6].ScriptArg":["1052657","1052655"],"Script[7].ScriptInstruction":["TARGET_DYLISE_05","TARGET_DYLISE_02"],"Script[7].ScriptArg":["1052671","1052670"],"Script[8].ScriptInstruction":["TARGET_DYLISE_06","TARGET_DYLISE_03"],"Script[8].ScriptArg":["1052658","1052656"],"Script[9].ScriptInstruction":["TARGET_DYLISE_07","TARGET_DYLISE_04"],"Script[9].ScriptArg":["1052672","1052657"],"Script[10].ScriptInstruction":["TARGET_DYLISE_08","TARGET_DYLISE_05"],"Script[10].ScriptArg":["1052659","1052671"],"Script[11].ScriptInstruction":["TARGET_DYLISE_09","TARGET_DYLISE_06"],"Script[11].ScriptArg":["1052673","1052658"],"Script[12].ScriptInstruction":["TARGET_DYLISE_10","TARGET_DYLISE_07"],"Script[12].ScriptArg":["1052664","1052672"],"Script[13].ScriptInstruction":["TARGET_DYLISE_11","TARGET_DYLISE_08"],"Script[13].ScriptArg":["1052665","1052659"],"Script[14].ScriptInstruction":["TARGET_DYLISE_12","TARGET_DYLISE_09"],"Script[14].ScriptArg":["1052674","1052673"],"Script[15].ScriptInstruction":["TARGET_DYLISE_13","TARGET_DYLISE_10"],"Script[15].ScriptArg":["1052666","1052664"],"Script[16].ScriptInstruction":["TARGET_DYLISE_14","TARGET_DYLISE_11"],"Script[16].ScriptArg":["1052675","1052665"],"Script[17].ScriptInstruction":["TARGET_DYLISE_15","TARGET_DYLISE_12"],"Script[17].ScriptArg":["1052667","1052674"],"Script[18].ScriptInstruction":["TARGET_DYLISE_16","TARGET_DYLISE_13"],"Script[18].ScriptArg":["1052676","1052666"],"Script[19].ScriptInstruction":["TARGET_DYLISE_17","TARGET_DYLISE_14"],"Script[19].ScriptArg":["1052668","1052675"],"Script[20].ScriptInstruction":["TARGET_DYLISE_18","TARGET_DYLISE_15"],"Script[20].ScriptArg":["1052677","1052667"],"Script[21].ScriptInstruction":["TARGET_DYLISE_19","TARGET_DYLISE_16"],"Script[21].ScriptArg":["1052678","1052676"],"Script[22].ScriptInstruction":["TARGET_DYLISE_20","TARGET_DYLISE_17"],"Script[22].ScriptArg":["1052679","1052668"],"Script[23].ScriptInstruction":["TARGET_DYLISE_21","TARGET_DYLISE_18"],"Script[23].ScriptArg":["1052669","1052677"],"Script[24].ScriptInstruction":["TARGET_DYLISE_22","TARGET_DYLISE_19"],"Script[24].ScriptArg":["1052680","1052678"],"Script[25].ScriptInstruction":["TARGET_DYLISE_23","TARGET_DYLISE_20"],"Script[25].ScriptArg":["1053377","1052679"],"Script[26].ScriptInstruction":["BIND_COMMAND_01","TARGET_DYLISE_21"],"Script[26].ScriptArg":["12239593","1052669"],"Script[27].ScriptInstruction":["","TARGET_DYLISE_22"],"Script[27].ScriptArg":["0","1052680"],"Script[28].ScriptInstruction":["","TARGET_DYLISE_23"],"Script[28].ScriptArg":["0","1053377"]}}}