{"rows_added":[3001,3002,3003,3004,3005,3006,3007,3008,3009,3010,3011,3012,3013,3014,3015,3016,3017,3018,3019,3020,3021,3022,3023,3024,3025,3026,3027,3028,3029,3030,3031,3032,3033,3034,3035,3036,3037,3038,3039,3040,3041,3042,3043,3044,3045,3046,3047,3048,3049,3050],"rows_removed":[],"rows_changed":{"666":{"Data[0]":["153","595"]},"2045":{"Action":["0","1322"],"Data[0]":["0","337"],"CondBattle":["False","True"],"CondPVP":["False","True"]},"2614":{"Action":["0","1322"],"Data[0]":["0","359"],"CondBattle":["False","True"],"CondPVP":["False","True"]},"2706":{"Action":["0","2633"],"Data[0]":["0","543"],"Data[1]":["0","5211"],"Data[2]":["0","291"],"CondBattle":["False","True"],"CondPVP":["False","True"]},"2776":{"Action":["0","2633"],"Data[0]":["0","553"],"Data[1]":["0","5211"],"Data[2]":["0","297"],"CondBattle":["False","True"],"CondPVP":["False","True"]},"2844":{"Action":["0","2633"],"Data[0]":["0","577"],"Data[1]":["0","5211"],"Data[2]":["0","308"],"CondBattle":["False","True"],"CondPVP":["False","True"]},"2845":{"Action":["0","2633"],"Data[0]":["0","583"],"Data[1]":["0","5211"],"Data[2]":["0","314"],"CondBattle":["False","True"],"CondPVP":["False","True"]},"2846":{"Action":["0","2633"],"Data[0]":["0","584"],"Data[1]":["0","5211"],"Data[2]":["0","315"],"CondBattle":["False","True"],"CondPVP":["False","True"]},"2847":{"Action":["0","2633"],"Data[0]":["0","585"],"Data[1]":["0","5211"],"Data[2]":["0","316"],"CondBattle":["False","True"],"CondPVP":["False","True"]},"2882":{"Action":["0","853"],"Data[0]":["0","579"],"CondBattle":["False","True"],"CondPVP":["False","True"]},"2892":{"Action":["0","18083"],"Data[0]":["0","3837"],"CondBattle":["False","True"],"CondPVP":["False","True"]},"2893":{"Action":["0","18083"],"Data[0]":["0","3838"],"CondBattle":["False","True"],"CondPVP":["False","True"]},"2894":{"Action":["0","18083"],"Data[0]":["0","3839"],"CondBattle":["False","True"],"CondPVP":["False","True"]},"2895":{"Action":["0","18083"],"Data[0]":["0","3840"],"CondBattle":["False","True"],"CondPVP":["False","True"]},"2896":{"Action":["0","18083"],"Data[0]":["0","3841"],"CondBattle":["False","True"],"CondPVP":["False","True"]},"2898":{"Action":["0","20086"],"Data[0]":["0","52"],"CondBattle":["False","True"],"CondPVP":["False","True"]},"2914":{"Action":["0","2633"],"Data[0]":["0","634"],"Data[1]":["0","10900"],"Data[2]":["0","14"],"CondBattle":["False","True"],"CondPVP":["False","True"]},"2945":{"Action":["0","3357"],"Data[0]":["0","465"],"CondBattle":["False","True"],"CondPVP":["False","True"]},"2946":{"Action":["0","3357"],"Data[0]":["0","466"],"CondBattle":["False","True"],"CondPVP":["False","True"]},"2947":{"Action":["0","3357"],"Data[0]":["0","467"],"CondBattle":["False","True"],"CondPVP":["False","True"]},"2948":{"Action":["0","3357"],"Data[0]":["0","468"],"CondBattle":["False","True"],"CondPVP":["False","True"]},"2949":{"Action":["0","3357"],"Data[0]":["0","469"],"CondBattle":["False","True"],"CondPVP":["False","True"]},"2950":{"Action":["0","3357"],"Data[0]":["0","470"],"CondBattle":["False","True"],"CondPVP":["False","True"]},"2951":{"Action":["0","3357"],"Data[0]":["0","471"],"CondBattle":["False","True"],"CondPVP":["False","True"]},"2952":{"Action":["0","3357"],"Data[0]":["0","472"],"CondBattle":["False","True"],"CondPVP":["False","True"]},"2953":{"Action":["0","3357"],"Data[0]":["0","473"],"CondBattle":["False","True"],"CondPVP":["False","True"]},"2958":{"Action":["0","2633"],"Data[0]":["0","642"],"Data[1]":["0","5211"],"Data[2]":["0","328"],"CondBattle":["False","True"],"CondPVP":["False","True"]},"2959":{"Action":["0","2633"],"Data[0]":["0","643"],"Data[1]":["0","5211"],"Data[2]":["0","329"],"CondBattle":["False","True"],"CondPVP":["False","True"]},"2973":{"Action":["0","1322"],"Data[0]":["0","417"],"CondBattle":["False","True"],"CondPVP":["False","True"]},"2974":{"Action":["0","1322"],"Data[0]":["0","420"],"CondBattle":["False","True"],"CondPVP":["False","True"]},"2977":{"Action":["0","1322"],"Data[0]":["0","432"],"CondBattle":["False","True"],"CondPVP":["False","True"]},"2985":{"Action":["0","1322"],"Data[0]":["0","444"],"CondBattle":["False","True"],"CondPVP":["False","True"]},"2989":{"Action":["0","1322"],"Data[0]":["0","419"],"CondBattle":["False","True"],"CondPVP":["False","True"]},"2993":{"Action":["0","853"],"Data[0]":["0","582"],"CondBattle":["False","True"],"CondPVP":["False","True"]},"2997":{"Action":["0","853"],"Data[0]":["0","580"],"CondBattle":["False","True"],"CondPVP":["False","True"]},"2998":{"Action":["0","853"],"Data[0]":["0","581"],"CondBattle":["False","True"],"CondPVP":["False","True"]},"3000":{"Action":["0","853"],"Data[0]":["0","584"],"CondBattle":["False","True"],"CondPVP":["False","True"]}}}