{"rows_added":[36,37,38,39,40,41,42],"rows_removed":[],"rows_changed":{"5":{"":["True","False"]},"6":{"":["True","False"]},"7":{"":["True","False"]},"8":{"":["True","False"]},"12":{"":["True","False"]},"13":{"":["True","False"]},"14":{"":["True","False"]},"15":{"":["True","False"]},"16":{"":["True","False"]},"17":{"":["True","False"]},"21":{"":["True","False"]},"22":{"":["True","False"]},"25":{"":["True","False"]},"26":{"UIPriority":["5","1"],"":["False","True"]},"27":{"UIPriority":["6","2"],"":["False","True"]},"29":{"":["True","False"]},"30":{"":["True","False"]}}}