{"rows_added":[],"rows_removed":[],"rows_changed":{"35243":{"EphemeralStartTime":["0","65535"],"EphemeralEndTime":["0","65535"]},"35244":{"EphemeralStartTime":["0","65535"],"EphemeralEndTime":["0","65535"]},"35245":{"EphemeralStartTime":["0","65535"],"EphemeralEndTime":["0","65535"]},"35246":{"EphemeralStartTime":["0","65535"],"EphemeralEndTime":["0","65535"]},"35247":{"EphemeralStartTime":["0","65535"],"EphemeralEndTime":["0","65535"]},"35248":{"EphemeralStartTime":["0","65535"],"EphemeralEndTime":["0","65535"]},"35249":{"EphemeralStartTime":["0","65535"],"EphemeralEndTime":["0","65535"]},"35250":{"EphemeralStartTime":["0","65535"],"EphemeralEndTime":["0","65535"]},"35251":{"EphemeralStartTime":["0","65535"],"EphemeralEndTime":["0","65535"]},"35252":{"EphemeralStartTime":["0","65535"],"EphemeralEndTime":["0","65535"]},"35253":{"EphemeralStartTime":["0","65535"],"EphemeralEndTime":["0","65535"]},"35254":{"EphemeralStartTime":["0","65535"],"EphemeralEndTime":["0","65535"]},"35255":{"EphemeralStartTime":["0","65535"],"EphemeralEndTime":["0","65535"]},"35256":{"EphemeralStartTime":["0","65535"],"EphemeralEndTime":["0","65535"]},"35257":{"EphemeralStartTime":["0","65535"],"EphemeralEndTime":["0","65535"]},"35258":{"EphemeralStartTime":["0","65535"],"EphemeralEndTime":["0","65535"]},"35259":{"EphemeralStartTime":["0","65535"],"EphemeralEndTime":["0","65535"]},"35260":{"EphemeralStartTime":["0","65535"],"EphemeralEndTime":["0","65535"]},"35261":{"EphemeralStartTime":["0","65535"],"EphemeralEndTime":["0","65535"]},"35262":{"EphemeralStartTime":["0","65535"],"EphemeralEndTime":["0","65535"]},"35263":{"EphemeralStartTime":["0","65535"],"EphemeralEndTime":["0","65535"]},"35264":{"EphemeralStartTime":["0","65535"],"EphemeralEndTime":["0","65535"]},"35265":{"EphemeralStartTime":["0","65535"],"EphemeralEndTime":["0","65535"]},"35266":{"EphemeralStartTime":["0","65535"],"EphemeralEndTime":["0","65535"]},"35267":{"EphemeralStartTime":["0","65535"],"EphemeralEndTime":["0","65535"]},"35268":{"EphemeralStartTime":["0","65535"],"EphemeralEndTime":["0","65535"]},"35269":{"EphemeralStartTime":["0","65535"],"EphemeralEndTime":["0","65535"]},"35270":{"EphemeralStartTime":["0","65535"],"EphemeralEndTime":["0","65535"]},"35271":{"EphemeralStartTime":["0","65535"],"EphemeralEndTime":["0","65535"]},"35272":{"EphemeralStartTime":["0","65535"],"EphemeralEndTime":["0","65535"]},"35273":{"EphemeralStartTime":["0","65535"],"EphemeralEndTime":["0","65535"]},"35274":{"EphemeralStartTime":["0","65535"],"EphemeralEndTime":["0","65535"]},"35275":{"EphemeralStartTime":["0","65535"],"EphemeralEndTime":["0","65535"]},"35276":{"EphemeralStartTime":["0","65535"],"EphemeralEndTime":["0","65535"]},"35277":{"EphemeralStartTime":["0","65535"],"EphemeralEndTime":["0","65535"]},"35278":{"EphemeralStartTime":["0","65535"],"EphemeralEndTime":["0","65535"]}}}